baeshade/__init__.py
baeshade/baeshade.py
baeshade/baeshadeapp.py
baeshade/baeshademath.py
baeshade/baeshadeutil.py
baeshade-0.0.1.dist-info/LICENSE
baeshade-0.0.1.dist-info/METADATA
baeshade-0.0.1.dist-info/WHEEL
baeshade-0.0.1.dist-info/top_level.txt
baeshade-0.0.1.dist-info/RECORD
